LICENSE
MANIFEST.in
README.md
runtests.py
setup.py
csvexport/__init__.py
csvexport/exporters.py
csvexport/shortcuts.py
django_csvexport.egg-info/PKG-INFO
django_csvexport.egg-info/SOURCES.txt
django_csvexport.egg-info/dependency_links.txt
django_csvexport.egg-info/not-zip-safe
django_csvexport.egg-info/requires.txt
django_csvexport.egg-info/top_level.txt
requirements/install.txt
requirements/tests.txt